portkeeper/__init__.py
portkeeper/cli.py
portkeeper/core.py
portkeeper-0.5.46.dist-info/licenses/LICENSE
portkeeper-0.5.46.dist-info/METADATA
portkeeper-0.5.46.dist-info/WHEEL
portkeeper-0.5.46.dist-info/entry_points.txt
portkeeper-0.5.46.dist-info/top_level.txt
portkeeper-0.5.46.dist-info/RECORD
