Metadata-Version: 2.4
Name: portkeeper
Version: 0.5.46
Summary: A tool to manage and reserve free ports for your applications
Author-email: Tom Sapletta <info@softreck.dev>
License: Apache-2.0
Project-URL: Homepage, https://github.com/dynapsys/portkeeper
Project-URL: Repository, https://github.com/dynapsys/portkeeper.git
Project-URL: Issues, https://github.com/dynapsys/portkeeper/issues
Keywords: port,reservation,management,networking
Classifier: Development Status :: 3 - Alpha
Classifier: Intended Audience :: Developers
Classifier: Topic :: Software Development :: Libraries :: Python Modules
Classifier: Programming Language :: Python :: 3
Classifier: Programming Language :: Python :: 3.8
Classifier: Programming Language :: Python :: 3.9
Classifier: Programming Language :: Python :: 3.10
Classifier: Programming Language :: Python :: 3.11
Classifier: Programming Language :: Python :: 3.12
Classifier: Operating System :: OS Independent
Requires-Python: >=3.8
License-File: LICENSE
Dynamic: license-file
